jguvc_eip/_BasicIOWindowUI.py
jguvc_eip/__init__.py
jguvc_eip/_io_messages.py
jguvc_eip/_io_window.py
jguvc_eip/_mylabel.py
jguvc_eip/basic_io.py
jguvc_eip/basic_io_error.py
jguvc_eip/colors.py
jguvc_eip/image_objects.py
jguvc_eip-1.1.dist-info/LICENSE.txt
jguvc_eip-1.1.dist-info/METADATA
jguvc_eip-1.1.dist-info/WHEEL
jguvc_eip-1.1.dist-info/top_level.txt
jguvc_eip-1.1.dist-info/RECORD
