Metadata-Version: 2.1
Name: jguvc-eip
Version: 1.1
Summary: A simple QT-based framework with basic input (keyboard) and output (drawing) capabilities made for educational purposes.
Home-page: https://luna.informatik.uni-mainz.de/eip23/
Author: Michael Wand
Author-email: wandm@uni-mainz.de
License: MIT
Classifier: Programming Language :: Python :: 3
Classifier: License :: OSI Approved :: MIT License
Classifier: Operating System :: OS Independent
License-File: LICENSE.txt
Requires-Dist: PyQt5
Requires-Dist: typeguard (==2.13.3)
